MANIFEST.in
README
setup.py
pascut/__init__.py
pascut/commands.py
pascut/main.py
pascut/plugin.py
pascut.egg-info/PKG-INFO
pascut.egg-info/SOURCES.txt
pascut.egg-info/dependency_links.txt
pascut.egg-info/entry_points.txt
pascut.egg-info/requires.txt
pascut.egg-info/top_level.txt
pascut/plugins/file_observer.py
pascut/plugins/flash_compiler.py
pascut/plugins/http_server.py
pascut/plugins/logger.py
pascut/plugins/js/swfobject.js