Metadata-Version: 1.0
Name: pascut
Version: 0.1
Summary: Automation Flash build tool
Home-page: http://bitbucket.org/mopemope/pascut/
Author: yutaka.matsubara
Author-email: yutaka.matsubara@gmail.com
License: MIT License
Platform: Any
Classifier: Topic :: Software Development :: Libraries :: Python Modules
Classifier: Intended Audience :: Developers
Classifier: License :: OSI Approved :: MIT License
Classifier: Programming Language :: Python
